sztestlib/__init__.py
sztestlib/szlibone.py
sztestlib20210724-1.0.0.dist-info/LICENSE.txt
sztestlib20210724-1.0.0.dist-info/METADATA
sztestlib20210724-1.0.0.dist-info/WHEEL
sztestlib20210724-1.0.0.dist-info/top_level.txt
sztestlib20210724-1.0.0.dist-info/RECORD
