Metadata-Version: 2.1
Name: sztestlib20210724
Version: 1.0.0
Summary: this is a niubi lib
Home-page: https://github.com/pypa/sampleproject
Author: Sz
Author-email: maweiustb@163.com
License: MIT
Platform: UNKNOWN
